CHANGELOG.md
README.md
mitol/__init__.py
mitol/payment_gateway/__init__.py
mitol/payment_gateway/api.py
mitol/payment_gateway/apps.py
mitol/payment_gateway/constants.py
mitol/payment_gateway/exceptions.py
mitol/payment_gateway/payment_utils.py
mitol/payment_gateway/py.typed
mitol/payment_gateway/settings/__init__.py
mitol/payment_gateway/settings/cybersource.py
mitol_django_payment_gateway-2025.3.17.dist-info/METADATA
mitol_django_payment_gateway-2025.3.17.dist-info/WHEEL
mitol_django_payment_gateway-2025.3.17.dist-info/RECORD
