Metadata-Version: 2.4
Name: mitol-django-payment-gateway
Version: 2025.3.17
Summary: Django application to handle payment processing
License-Expression: BSD-3-Clause
Requires-Python: >=3.10
Requires-Dist: cybersource-rest-client-python>=0.0.59
Requires-Dist: django-stubs>=1.13.1
Requires-Dist: django>=3.0
Requires-Dist: mitol-django-common
